{
  "manifestVersion": "3.2",
  "proxies": [
    {
      "address": "0xf0F4aE40Db8217945fEF1F5Cea089d103181399C",
      "txHash": "0xb4b0d32753a801231092df1ea2c6bcdeef3435e9271c305af35527406e9560e8",
      "kind": "uups"
    },
    {
      "address": "0x9531375B31F4c6c49c2dB26E8D397363C88f9D6A",
      "txHash": "0x0fb7969726feb9e1151094640ac966f48961e2e2c6d0ef79fc8cc55bc7712cd1",
      "kind": "uups"
    },
    {
      "address": "0xcdd88Be0ea92C85ffeaD05093AC9e566132ef1AC",
      "txHash": "0x016fc8b232565d7ac4fddc88f602931505858c1026009d4ddf5ff408a4ecdef5",
      "kind": "uups"
    },
    {
      "address": "0xcEEA7cb32cA4172099BE1e0C682EcAc0C3A3f2C1",
      "txHash": "0xac958aa50291f3a52f970c53024a917a467077f73748a4c0f845eca95df9fad6",
      "kind": "uups"
    }
  ],
  "impls": {
    "fe0e0b3ec6ae332066f0de86aebb06b5e6d686330a5dbfcd011ed3eca5a1e49f": {
      "address": "0xA932ed0E0A02EB31E61208A1a5D64bf2E7bb9F1C",
      "txHash": "0xd9209ab8f613ffde8b037d5350eaa37f6da5d9a16bdbe92e723d5556724c3778",
      "layout": {
        "solcVersion": "0.8.28",
        "storage": [
          {
            "label": "_nextTokenId",
            "offset": 0,
            "slot": "0",
            "type": "t_uint256",
            "contract": "BusinessCard",
            "src": "contracts\\BusinessCard.sol:14"
          },
          {
            "label": "businessCards",
            "offset": 0,
            "slot": "1",
            "type": "t_mapping(t_uint256,t_struct(CardDetails)7920_storage)",
            "contract": "BusinessCard",
            "src": "contracts\\BusinessCard.sol:30"
          },
          {
            "label": "userCard",
            "offset": 0,
            "slot": "2",
            "type": "t_mapping(t_address,t_uint256)",
            "contract": "BusinessCard",
            "src": "contracts\\BusinessCard.sol:31"
          },
          {
            "label": "receivedCards",
            "offset": 0,
            "slot": "3",
            "type": "t_mapping(t_address,t_mapping(t_uint256,t_bool))",
            "contract": "BusinessCard",
            "src": "contracts\\BusinessCard.sol:32"
          },
          {
            "label": "userReceivedCards",
            "offset": 0,
            "slot": "4",
            "type": "t_mapping(t_address,t_array(t_uint256)dyn_storage)",
            "contract": "BusinessCard",
            "src": "contracts\\BusinessCard.sol:33"
          },
          {
            "label": "cardRentals",
            "offset": 0,
            "slot": "5",
            "type": "t_mapping(t_uint256,t_struct(Rental)7929_storage)",
            "contract": "BusinessCard",
            "src": "contracts\\BusinessCard.sol:34"
          },
          {
            "label": "userRentedCards",
            "offset": 0,
            "slot": "6",
            "type": "t_mapping(t_address,t_array(t_uint256)dyn_storage)",
            "contract": "BusinessCard",
            "src": "contracts\\BusinessCard.sol:35"
          },
          {
            "label": "__gap",
            "offset": 0,
            "slot": "7",
            "type": "t_array(t_uint256)50_storage",
            "contract": "BusinessCard",
            "src": "contracts\\BusinessCard.sol:194"
          }
        ],
        "types": {
          "t_address": {
            "label": "address",
            "numberOfBytes": "20"
          },
          "t_bool": {
            "label": "bool",
            "numberOfBytes": "1"
          },
          "t_mapping(t_address,t_bool)": {
            "label": "mapping(address => bool)",
            "numberOfBytes": "32"
          },
          "t_mapping(t_address,t_mapping(t_address,t_bool))": {
            "label": "mapping(address => mapping(address => bool))",
            "numberOfBytes": "32"
          },
          "t_mapping(t_address,t_uint256)": {
            "label": "mapping(address => uint256)",
            "numberOfBytes": "32"
          },
          "t_mapping(t_uint256,t_address)": {
            "label": "mapping(uint256 => address)",
            "numberOfBytes": "32"
          },
          "t_mapping(t_uint256,t_string_storage)": {
            "label": "mapping(uint256 => string)",
            "numberOfBytes": "32"
          },
          "t_string_storage": {
            "label": "string",
            "numberOfBytes": "32"
          },
          "t_struct(ERC721Storage)235_storage": {
            "label": "struct ERC721Upgradeable.ERC721Storage",
            "members": [
              {
                "label": "_name",
                "type": "t_string_storage",
                "offset": 0,
                "slot": "0"
              },
              {
                "label": "_symbol",
                "type": "t_string_storage",
                "offset": 0,
                "slot": "1"
              },
              {
                "label": "_owners",
                "type": "t_mapping(t_uint256,t_address)",
                "offset": 0,
                "slot": "2"
              },
              {
                "label": "_balances",
                "type": "t_mapping(t_address,t_uint256)",
                "offset": 0,
                "slot": "3"
              },
              {
                "label": "_tokenApprovals",
                "type": "t_mapping(t_uint256,t_address)",
                "offset": 0,
                "slot": "4"
              },
              {
                "label": "_operatorApprovals",
                "type": "t_mapping(t_address,t_mapping(t_address,t_bool))",
                "offset": 0,
                "slot": "5"
              }
            ],
            "numberOfBytes": "192"
          },
          "t_struct(ERC721URIStorageStorage)544_storage": {
            "label": "struct ERC721URIStorageUpgradeable.ERC721URIStorageStorage",
            "members": [
              {
                "label": "_tokenURIs",
                "type": "t_mapping(t_uint256,t_string_storage)",
                "offset": 0,
                "slot": "0"
              }
            ],
            "numberOfBytes": "32"
          },
          "t_struct(InitializableStorage)73_storage": {
            "label": "struct Initializable.InitializableStorage",
            "members": [
              {
                "label": "_initialized",
                "type": "t_uint64",
                "offset": 0,
                "slot": "0"
              },
              {
                "label": "_initializing",
                "type": "t_bool",
                "offset": 8,
                "slot": "0"
              }
            ],
            "numberOfBytes": "32"
          },
          "t_struct(OwnableStorage)13_storage": {
            "label": "struct OwnableUpgradeable.OwnableStorage",
            "members": [
              {
                "label": "_owner",
                "type": "t_address",
                "offset": 0,
                "slot": "0"
              }
            ],
            "numberOfBytes": "32"
          },
          "t_uint256": {
            "label": "uint256",
            "numberOfBytes": "32"
          },
          "t_uint64": {
            "label": "uint64",
            "numberOfBytes": "8"
          },
          "t_array(t_uint256)50_storage": {
            "label": "uint256[50]",
            "numberOfBytes": "1600"
          },
          "t_array(t_uint256)dyn_storage": {
            "label": "uint256[]",
            "numberOfBytes": "32"
          },
          "t_mapping(t_address,t_array(t_uint256)dyn_storage)": {
            "label": "mapping(address => uint256[])",
            "numberOfBytes": "32"
          },
          "t_mapping(t_address,t_mapping(t_uint256,t_bool))": {
            "label": "mapping(address => mapping(uint256 => bool))",
            "numberOfBytes": "32"
          },
          "t_mapping(t_uint256,t_bool)": {
            "label": "mapping(uint256 => bool)",
            "numberOfBytes": "32"
          },
          "t_mapping(t_uint256,t_struct(CardDetails)7920_storage)": {
            "label": "mapping(uint256 => struct BusinessCard.CardDetails)",
            "numberOfBytes": "32"
          },
          "t_mapping(t_uint256,t_struct(Rental)7929_storage)": {
            "label": "mapping(uint256 => struct BusinessCard.Rental)",
            "numberOfBytes": "32"
          },
          "t_struct(CardDetails)7920_storage": {
            "label": "struct BusinessCard.CardDetails",
            "members": [
              {
                "label": "name",
                "type": "t_string_storage",
                "offset": 0,
                "slot": "0"
              },
              {
                "label": "title",
                "type": "t_string_storage",
                "offset": 0,
                "slot": "1"
              },
              {
                "label": "company",
                "type": "t_string_storage",
                "offset": 0,
                "slot": "2"
              },
              {
                "label": "contactInfo",
                "type": "t_string_storage",
                "offset": 0,
                "slot": "3"
              }
            ],
            "numberOfBytes": "128"
          },
          "t_struct(Rental)7929_storage": {
            "label": "struct BusinessCard.Rental",
            "members": [
              {
                "label": "renter",
                "type": "t_address",
                "offset": 0,
                "slot": "0"
              },
              {
                "label": "startTime",
                "type": "t_uint256",
                "offset": 0,
                "slot": "1"
              },
              {
                "label": "endTime",
                "type": "t_uint256",
                "offset": 0,
                "slot": "2"
              },
              {
                "label": "isActive",
                "type": "t_bool",
                "offset": 0,
                "slot": "3"
              }
            ],
            "numberOfBytes": "128"
          }
        },
        "namespaces": {
          "erc7201:openzeppelin.storage.Ownable": [
            {
              "contract": "OwnableUpgradeable",
              "label": "_owner",
              "type": "t_address",
              "src": "@openzeppelin\\contracts-upgradeable\\access\\OwnableUpgradeable.sol:24",
              "offset": 0,
              "slot": "0"
            }
          ],
          "erc7201:openzeppelin.storage.ERC721URIStorage": [
            {
              "contract": "ERC721URIStorageUpgradeable",
              "label": "_tokenURIs",
              "type": "t_mapping(t_uint256,t_string_storage)",
              "src": "@openzeppelin\\contracts-upgradeable\\token\\ERC721\\extensions\\ERC721URIStorageUpgradeable.sol:25",
              "offset": 0,
              "slot": "0"
            }
          ],
          "erc7201:openzeppelin.storage.ERC721": [
            {
              "contract": "ERC721Upgradeable",
              "label": "_name",
              "type": "t_string_storage",
              "src": "@openzeppelin\\contracts-upgradeable\\token\\ERC721\\ERC721Upgradeable.sol:27",
              "offset": 0,
              "slot": "0"
            },
            {
              "contract": "ERC721Upgradeable",
              "label": "_symbol",
              "type": "t_string_storage",
              "src": "@openzeppelin\\contracts-upgradeable\\token\\ERC721\\ERC721Upgradeable.sol:30",
              "offset": 0,
              "slot": "1"
            },
            {
              "contract": "ERC721Upgradeable",
              "label": "_owners",
              "type": "t_mapping(t_uint256,t_address)",
              "src": "@openzeppelin\\contracts-upgradeable\\token\\ERC721\\ERC721Upgradeable.sol:32",
              "offset": 0,
              "slot": "2"
            },
            {
              "contract": "ERC721Upgradeable",
              "label": "_balances",
              "type": "t_mapping(t_address,t_uint256)",
              "src": "@openzeppelin\\contracts-upgradeable\\token\\ERC721\\ERC721Upgradeable.sol:34",
              "offset": 0,
              "slot": "3"
            },
            {
              "contract": "ERC721Upgradeable",
              "label": "_tokenApprovals",
              "type": "t_mapping(t_uint256,t_address)",
              "src": "@openzeppelin\\contracts-upgradeable\\token\\ERC721\\ERC721Upgradeable.sol:36",
              "offset": 0,
              "slot": "4"
            },
            {
              "contract": "ERC721Upgradeable",
              "label": "_operatorApprovals",
              "type": "t_mapping(t_address,t_mapping(t_address,t_bool))",
              "src": "@openzeppelin\\contracts-upgradeable\\token\\ERC721\\ERC721Upgradeable.sol:38",
              "offset": 0,
              "slot": "5"
            }
          ],
          "erc7201:openzeppelin.storage.Initializable": [
            {
              "contract": "Initializable",
              "label": "_initialized",
              "type": "t_uint64",
              "src": "@openzeppelin\\contracts-upgradeable\\proxy\\utils\\Initializable.sol:69",
              "offset": 0,
              "slot": "0"
            },
            {
              "contract": "Initializable",
              "label": "_initializing",
              "type": "t_bool",
              "src": "@openzeppelin\\contracts-upgradeable\\proxy\\utils\\Initializable.sol:73",
              "offset": 8,
              "slot": "0"
            }
          ]
        }
      }
    },
    "d3a8388f57feb67ed10616ef6e576c5ed7ef54020118ef441315fc81e7667c1a": {
      "address": "0x69654089961C8A3506896038A99abD40f042aB51",
      "txHash": "0x92b4251e6fb0ff668646f480956a9d23289cfb043cec0252060945aca53db912",
      "layout": {
        "solcVersion": "0.8.28",
        "storage": [
          {
            "label": "_nextTokenId",
            "offset": 0,
            "slot": "0",
            "type": "t_uint256",
            "contract": "BusinessCard",
            "src": "contracts\\BusinessCard.sol:13"
          },
          {
            "label": "businessCards",
            "offset": 0,
            "slot": "1",
            "type": "t_mapping(t_uint256,t_struct(CardDetails)8717_storage)",
            "contract": "BusinessCard",
            "src": "contracts\\BusinessCard.sol:29"
          },
          {
            "label": "userCard",
            "offset": 0,
            "slot": "2",
            "type": "t_mapping(t_address,t_uint256)",
            "contract": "BusinessCard",
            "src": "contracts\\BusinessCard.sol:30"
          },
          {
            "label": "receivedCards",
            "offset": 0,
            "slot": "3",
            "type": "t_mapping(t_address,t_mapping(t_uint256,t_bool))",
            "contract": "BusinessCard",
            "src": "contracts\\BusinessCard.sol:31"
          },
          {
            "label": "userReceivedCards",
            "offset": 0,
            "slot": "4",
            "type": "t_mapping(t_address,t_array(t_uint256)dyn_storage)",
            "contract": "BusinessCard",
            "src": "contracts\\BusinessCard.sol:32"
          },
          {
            "label": "cardRentals",
            "offset": 0,
            "slot": "5",
            "type": "t_mapping(t_uint256,t_struct(Rental)8726_storage)",
            "contract": "BusinessCard",
            "src": "contracts\\BusinessCard.sol:33"
          },
          {
            "label": "userRentedCards",
            "offset": 0,
            "slot": "6",
            "type": "t_mapping(t_address,t_array(t_uint256)dyn_storage)",
            "contract": "BusinessCard",
            "src": "contracts\\BusinessCard.sol:34"
          },
          {
            "label": "approvedCardSenders",
            "offset": 0,
            "slot": "7",
            "type": "t_mapping(t_address,t_bool)",
            "contract": "BusinessCard",
            "src": "contracts\\BusinessCard.sol:35"
          },
          {
            "label": "__gap",
            "offset": 0,
            "slot": "8",
            "type": "t_array(t_uint256)50_storage",
            "contract": "BusinessCard",
            "src": "contracts\\BusinessCard.sol:185"
          }
        ],
        "types": {
          "t_address": {
            "label": "address",
            "numberOfBytes": "20"
          },
          "t_bool": {
            "label": "bool",
            "numberOfBytes": "1"
          },
          "t_mapping(t_address,t_bool)": {
            "label": "mapping(address => bool)",
            "numberOfBytes": "32"
          },
          "t_mapping(t_address,t_mapping(t_address,t_bool))": {
            "label": "mapping(address => mapping(address => bool))",
            "numberOfBytes": "32"
          },
          "t_mapping(t_address,t_uint256)": {
            "label": "mapping(address => uint256)",
            "numberOfBytes": "32"
          },
          "t_mapping(t_uint256,t_address)": {
            "label": "mapping(uint256 => address)",
            "numberOfBytes": "32"
          },
          "t_mapping(t_uint256,t_string_storage)": {
            "label": "mapping(uint256 => string)",
            "numberOfBytes": "32"
          },
          "t_string_storage": {
            "label": "string",
            "numberOfBytes": "32"
          },
          "t_struct(ERC721Storage)235_storage": {
            "label": "struct ERC721Upgradeable.ERC721Storage",
            "members": [
              {
                "label": "_name",
                "type": "t_string_storage",
                "offset": 0,
                "slot": "0"
              },
              {
                "label": "_symbol",
                "type": "t_string_storage",
                "offset": 0,
                "slot": "1"
              },
              {
                "label": "_owners",
                "type": "t_mapping(t_uint256,t_address)",
                "offset": 0,
                "slot": "2"
              },
              {
                "label": "_balances",
                "type": "t_mapping(t_address,t_uint256)",
                "offset": 0,
                "slot": "3"
              },
              {
                "label": "_tokenApprovals",
                "type": "t_mapping(t_uint256,t_address)",
                "offset": 0,
                "slot": "4"
              },
              {
                "label": "_operatorApprovals",
                "type": "t_mapping(t_address,t_mapping(t_address,t_bool))",
                "offset": 0,
                "slot": "5"
              }
            ],
            "numberOfBytes": "192"
          },
          "t_struct(ERC721URIStorageStorage)544_storage": {
            "label": "struct ERC721URIStorageUpgradeable.ERC721URIStorageStorage",
            "members": [
              {
                "label": "_tokenURIs",
                "type": "t_mapping(t_uint256,t_string_storage)",
                "offset": 0,
                "slot": "0"
              }
            ],
            "numberOfBytes": "32"
          },
          "t_struct(InitializableStorage)73_storage": {
            "label": "struct Initializable.InitializableStorage",
            "members": [
              {
                "label": "_initialized",
                "type": "t_uint64",
                "offset": 0,
                "slot": "0"
              },
              {
                "label": "_initializing",
                "type": "t_bool",
                "offset": 8,
                "slot": "0"
              }
            ],
            "numberOfBytes": "32"
          },
          "t_struct(OwnableStorage)13_storage": {
            "label": "struct OwnableUpgradeable.OwnableStorage",
            "members": [
              {
                "label": "_owner",
                "type": "t_address",
                "offset": 0,
                "slot": "0"
              }
            ],
            "numberOfBytes": "32"
          },
          "t_uint256": {
            "label": "uint256",
            "numberOfBytes": "32"
          },
          "t_uint64": {
            "label": "uint64",
            "numberOfBytes": "8"
          },
          "t_array(t_uint256)50_storage": {
            "label": "uint256[50]",
            "numberOfBytes": "1600"
          },
          "t_array(t_uint256)dyn_storage": {
            "label": "uint256[]",
            "numberOfBytes": "32"
          },
          "t_mapping(t_address,t_array(t_uint256)dyn_storage)": {
            "label": "mapping(address => uint256[])",
            "numberOfBytes": "32"
          },
          "t_mapping(t_address,t_mapping(t_uint256,t_bool))": {
            "label": "mapping(address => mapping(uint256 => bool))",
            "numberOfBytes": "32"
          },
          "t_mapping(t_uint256,t_bool)": {
            "label": "mapping(uint256 => bool)",
            "numberOfBytes": "32"
          },
          "t_mapping(t_uint256,t_struct(CardDetails)8717_storage)": {
            "label": "mapping(uint256 => struct BusinessCard.CardDetails)",
            "numberOfBytes": "32"
          },
          "t_mapping(t_uint256,t_struct(Rental)8726_storage)": {
            "label": "mapping(uint256 => struct BusinessCard.Rental)",
            "numberOfBytes": "32"
          },
          "t_struct(CardDetails)8717_storage": {
            "label": "struct BusinessCard.CardDetails",
            "members": [
              {
                "label": "name",
                "type": "t_string_storage",
                "offset": 0,
                "slot": "0"
              },
              {
                "label": "title",
                "type": "t_string_storage",
                "offset": 0,
                "slot": "1"
              },
              {
                "label": "company",
                "type": "t_string_storage",
                "offset": 0,
                "slot": "2"
              },
              {
                "label": "contactInfo",
                "type": "t_string_storage",
                "offset": 0,
                "slot": "3"
              }
            ],
            "numberOfBytes": "128"
          },
          "t_struct(Rental)8726_storage": {
            "label": "struct BusinessCard.Rental",
            "members": [
              {
                "label": "renter",
                "type": "t_address",
                "offset": 0,
                "slot": "0"
              },
              {
                "label": "startTime",
                "type": "t_uint256",
                "offset": 0,
                "slot": "1"
              },
              {
                "label": "endTime",
                "type": "t_uint256",
                "offset": 0,
                "slot": "2"
              },
              {
                "label": "isActive",
                "type": "t_bool",
                "offset": 0,
                "slot": "3"
              }
            ],
            "numberOfBytes": "128"
          }
        },
        "namespaces": {
          "erc7201:openzeppelin.storage.Ownable": [
            {
              "contract": "OwnableUpgradeable",
              "label": "_owner",
              "type": "t_address",
              "src": "@openzeppelin\\contracts-upgradeable\\access\\OwnableUpgradeable.sol:24",
              "offset": 0,
              "slot": "0"
            }
          ],
          "erc7201:openzeppelin.storage.ERC721URIStorage": [
            {
              "contract": "ERC721URIStorageUpgradeable",
              "label": "_tokenURIs",
              "type": "t_mapping(t_uint256,t_string_storage)",
              "src": "@openzeppelin\\contracts-upgradeable\\token\\ERC721\\extensions\\ERC721URIStorageUpgradeable.sol:25",
              "offset": 0,
              "slot": "0"
            }
          ],
          "erc7201:openzeppelin.storage.ERC721": [
            {
              "contract": "ERC721Upgradeable",
              "label": "_name",
              "type": "t_string_storage",
              "src": "@openzeppelin\\contracts-upgradeable\\token\\ERC721\\ERC721Upgradeable.sol:27",
              "offset": 0,
              "slot": "0"
            },
            {
              "contract": "ERC721Upgradeable",
              "label": "_symbol",
              "type": "t_string_storage",
              "src": "@openzeppelin\\contracts-upgradeable\\token\\ERC721\\ERC721Upgradeable.sol:30",
              "offset": 0,
              "slot": "1"
            },
            {
              "contract": "ERC721Upgradeable",
              "label": "_owners",
              "type": "t_mapping(t_uint256,t_address)",
              "src": "@openzeppelin\\contracts-upgradeable\\token\\ERC721\\ERC721Upgradeable.sol:32",
              "offset": 0,
              "slot": "2"
            },
            {
              "contract": "ERC721Upgradeable",
              "label": "_balances",
              "type": "t_mapping(t_address,t_uint256)",
              "src": "@openzeppelin\\contracts-upgradeable\\token\\ERC721\\ERC721Upgradeable.sol:34",
              "offset": 0,
              "slot": "3"
            },
            {
              "contract": "ERC721Upgradeable",
              "label": "_tokenApprovals",
              "type": "t_mapping(t_uint256,t_address)",
              "src": "@openzeppelin\\contracts-upgradeable\\token\\ERC721\\ERC721Upgradeable.sol:36",
              "offset": 0,
              "slot": "4"
            },
            {
              "contract": "ERC721Upgradeable",
              "label": "_operatorApprovals",
              "type": "t_mapping(t_address,t_mapping(t_address,t_bool))",
              "src": "@openzeppelin\\contracts-upgradeable\\token\\ERC721\\ERC721Upgradeable.sol:38",
              "offset": 0,
              "slot": "5"
            }
          ],
          "erc7201:openzeppelin.storage.Initializable": [
            {
              "contract": "Initializable",
              "label": "_initialized",
              "type": "t_uint64",
              "src": "@openzeppelin\\contracts-upgradeable\\proxy\\utils\\Initializable.sol:69",
              "offset": 0,
              "slot": "0"
            },
            {
              "contract": "Initializable",
              "label": "_initializing",
              "type": "t_bool",
              "src": "@openzeppelin\\contracts-upgradeable\\proxy\\utils\\Initializable.sol:73",
              "offset": 8,
              "slot": "0"
            }
          ]
        }
      }
    }
  }
}
